calculator/__init__.py
calculator/calculator.py
calculator_devops_pucminas-0.0.3.dist-info/LICENSE
calculator_devops_pucminas-0.0.3.dist-info/METADATA
calculator_devops_pucminas-0.0.3.dist-info/WHEEL
calculator_devops_pucminas-0.0.3.dist-info/top_level.txt
calculator_devops_pucminas-0.0.3.dist-info/RECORD
