Metadata-Version: 2.1
Name: calculator-devops-pucminas
Version: 0.0.3
Summary: Python calculator software
Author-email: Sylvio Rubens <srjneto@hotmail.com>
Project-URL: Homepage, https://github.com/SylvioRubens/devops_project
Project-URL: Bug Tracker, https://github.com/SylvioRubens/devops_project/issues
Classifier: Programming Language :: Python :: 3
Classifier: License :: OSI Approved :: MIT License
Classifier: Operating System :: OS Independent
Requires-Python: >=3.9
License-File: LICENSE
Requires-Dist: Unidecode (==1.3.6)
Requires-Dist: pytest (==7.4.0)
Requires-Dist: flake8 (==6.0.0)
Requires-Dist: build
Requires-Dist: twine
